setup.py
tochsdk/__init__.py
tochsdk/tochsdk.py
tochsdk/tochsdk_click.py
tochsdk.egg-info/PKG-INFO
tochsdk.egg-info/SOURCES.txt
tochsdk.egg-info/dependency_links.txt
tochsdk.egg-info/entry_points.txt
tochsdk.egg-info/requires.txt
tochsdk.egg-info/top_level.txt