Metadata-Version: 2.1
Name: tochsdk
Version: 0.1.0
Summary: Toch ai commond line interface
Home-page: UNKNOWN
Author: toch team
License: MIT
Platform: UNKNOWN
